zalgolib/__init__.py
zalgolib/diacritics.py
zalgolib/zalgolib.py
zalgolib-0.2.2.dist-info/LICENSE
zalgolib-0.2.2.dist-info/METADATA
zalgolib-0.2.2.dist-info/WHEEL
zalgolib-0.2.2.dist-info/top_level.txt
zalgolib-0.2.2.dist-info/RECORD
