Metadata-Version: 2.1
Name: zalgolib
Version: 0.2.2
Summary: A Python library for a _FULL_ Zalgo experience
Author-email: Yatri Trivedi <jivanyatra@gmail.com>
License: MIT License
Project-URL: Homepage, https://github.com/jivanyatra/zalgolib/
Project-URL: Issues, https://github.com/jivanyatra/zalgolib/issues
Keywords: diacritics,horror,language encoding,obfuscation,text processing,zalgo
Classifier: Programming Language :: Python :: 3
Classifier: Topic :: Text Processing :: General
Classifier: Natural Language :: English
Classifier: Operating System :: POSIX :: Linux
Classifier: Programming Language :: Python :: 3.7
Classifier: Programming Language :: Python :: 3.8
Classifier: Programming Language :: Python :: 3.9
Requires-Python: >=3.7
License-File: LICENSE
